<PolymerNanocomposite>
    <ID>L262_S10_Liang_2014</ID>
    <DATA_SOURCE>
        <Citation>
            <CommonFields>
                <CitationType>research article</CitationType>
                <Publication>Macromolecules</Publication>
                <Title>High Ion Content Siloxane Phosphonium Ionomers with Very Low Tg</Title>
                <Author>Liang, Siwei</Author>
                <Author>O&#8217;Reilly, Michael V.</Author>
                <Author>Choi, U Hyeok</Author>
                <Author>Shiau, Huai-Suen</Author>
                <Author>Bartels, Joshua</Author>
                <Author>Chen, Quan</Author>
                <Author>Runt, James</Author>
                <Author>Winey, Karen I.</Author>
                <Author>Colby, Ralph H.</Author>
                <Publisher>American Chemical Society</Publisher>
                <PublicationYear>2014</PublicationYear>
                <DOI>10.1021/ma5001546</DOI>
                <URL>http://pubs.acs.org/doi/abs/10.1021/ma5001546</URL>
                <Language>English</Language>
                <DateOfCitation>08/01/2017</DateOfCitation>
            </CommonFields>
        </Citation>
    </DATA_SOURCE>
    <MATERIALS>
        <Matrix>
            <MatrixComponent>
                <ChemicalName>poly(ethylene oxide)</ChemicalName>
                <Abbreviation>PEO</Abbreviation>
            </MatrixComponent>
            <MatrixProcessing>
                <ChooseParameter>
                    <Mixing>
                        <MixingMethod>stirring</MixingMethod>
                        <ChemicalUsed>NaH</ChemicalUsed>
                        <ChemicalUsed>dry THF</ChemicalUsed>
                        <ChemicalUsed>tri(ethylene glycol) methyl ether</ChemicalUsed>
                        <Time>
                            <value>3</value>
                            <unit>hours</unit>
                        </Time>
                        <Temperature>
                            <value>0</value>
                            <unit>Celsius</unit>
                        </Temperature>
                    </Mixing>
                </ChooseParameter>
                <ChooseParameter>
                    <Additive>
                        <Description>the mixture was allowed to react overnight to complete the reaction</Description>
                        <Additive>allyl bromide</Additive>
                    </Additive>
                </ChooseParameter>
                <ChooseParameter>
                    <AmbientCondition>vacuum</AmbientCondition>
                </ChooseParameter>
                <ChooseParameter>
                    <Drying-Evaporation>
                        <Description>liquid was then purified by vacuum distillation</Description>
                    </Drying-Evaporation>
                </ChooseParameter>
            </MatrixProcessing>
            <Description>mol % of phosphonium: 11, PEOx side chain degree of polymerization: 3</Description>
        </Matrix>
        <Filler>
            <FillerComponent>
                <ChemicalName>bis- (trifluoromethanesulfonyl)imide</ChemicalName>
                <Abbreviation>TFSI-</Abbreviation>
            </FillerComponent>
        </Filler>
    </MATERIALS>
    <PROCESSING>
        <SolutionProcessing>
            <ChooseParameter>
                <Mixing>
                    <MixingMethod>stirring</MixingMethod>
                    <ChemicalUsed>PMHS</ChemicalUsed>
                    <ChemicalUsed>ATPB</ChemicalUsed>
                    <ChemicalUsed>vinyl PEO</ChemicalUsed>
                    <ChemicalUsed>anhydrous CH3CN</ChemicalUsed>
                    <ChemicalUsed>Pt[dvs] catalyst</ChemicalUsed>
                    <Temperature>
                        <value>90</value>
                        <unit>Celsius</unit>
                    </Temperature>
                </Mixing>
            </ChooseParameter>
            <ChooseParameter>
                <Additive>
                    <Description>residue was dissolved in DI water and dialyzed against ultrapure water for at least 1 week to remove impurities</Description>
                    <Additive>DI water</Additive>
                </Additive>
            </ChooseParameter>
            <ChooseParameter>
                <Additive>
                    <Description>prepared by dialysis in DI water with an over 50-fold excess of LiTFSI salt</Description>
                    <Additive>TFSI-</Additive>
                </Additive>
            </ChooseParameter>
        </SolutionProcessing>
    </PROCESSING>
    <CHARACTERIZATION>
        <Dielectric_and_Impedance_Spectroscopy_Analysis>
            <Equipment>Novocontrol GmbH Concept 40 broadband dielectric spectrometer</Equipment>
        </Dielectric_and_Impedance_Spectroscopy_Analysis>
        <Differential_Scanning_Calorimetry>
            <Equipment>Q2000</Equipment>
            <Description>TA</Description>
            <HeatingRate>
                <value>10</value>
                <unit>K/min</unit>
            </HeatingRate>
        </Differential_Scanning_Calorimetry>
        <XRay_Diffraction_and_Scattering>
            <Equipment>Nonius FR-591 rotating anode generator</Equipment>
            <Description>operating at 40 kV and 85 mA</Description>
        </XRay_Diffraction_and_Scattering>
    </CHARACTERIZATION>
    <PROPERTIES>
        <Electrical>
            <ElectricConductivity>
                <data>
                    <description>temperature dependence of DC conductivity</description>
                    <data>
                        <headers>
                            <column id="0">Tg/T</column>
                            <column id="1">DC conductivity (S/cm)</column>
                        </headers>
                        <rows>
                            <row id="0">
                                <column id="0">0.488942394654</column>
                                <column id="1">0.000231404599023</column>
                            </row>
                            <row id="1">
                                <column id="0">0.503661978561</column>
                                <column id="1">0.000202403106</column>
                            </row>
                            <row id="2">
                                <column id="0">0.517680792416</column>
                                <column id="1">0.000177030749509</column>
                            </row>
                            <row id="3">
                                <column id="0">0.532406064391</column>
                                <column id="1">0.000123734671075</column>
                            </row>
                            <row id="4">
                                <column id="0">0.547824143121</column>
                                <column id="1">0.000118388969651</column>
                            </row>
                            <row id="5">
                                <column id="0">0.563952092811</column>
                                <column id="1">7.91226357953e-05</column>
                            </row>
                            <row id="6">
                                <column id="0">0.580777399711</column>
                                <column id="1">6.04986098177e-05</column>
                            </row>
                            <row id="7">
                                <column id="0">0.593394673465</column>
                                <column id="1">5.29114456881e-05</column>
                            </row>
                            <row id="8">
                                <column id="0">0.603913049908</column>
                                <column id="1">4.04456122873e-05</column>
                            </row>
                            <row id="9">
                                <column id="0">0.617231093713</column>
                                <column id="1">3.53744175945e-05</column>
                            </row>
                            <row id="10">
                                <column id="0">0.629852917922</column>
                                <column id="1">2.58566074248e-05</column>
                            </row>
                            <row id="11">
                                <column id="0">0.640372431979</column>
                                <column id="1">1.889786886e-05</column>
                            </row>
                            <row id="12">
                                <column id="0">0.652290073296</column>
                                <column id="1">1.58023950556e-05</column>
                            </row>
                            <row id="13">
                                <column id="0">0.663510357404</column>
                                <column id="1">1.1549890196e-05</column>
                            </row>
                            <row id="14">
                                <column id="0">0.676127631158</column>
                                <column id="1">1.01014120762e-05</column>
                            </row>
                            <row id="15">
                                <column id="0">0.689452500646</column>
                                <column id="1">6.75020540077e-06</column>
                            </row>
                            <row id="16">
                                <column id="0">0.700673922367</column>
                                <column id="1">4.71727756999e-06</column>
                            </row>
                            <row id="17">
                                <column id="0">0.712596114139</column>
                                <column id="1">3.29670074331e-06</column>
                            </row>
                            <row id="18">
                                <column id="0">0.725919846013</column>
                                <column id="1">2.30406604296e-06</column>
                            </row>
                            <row id="19">
                                <column id="0">0.739249265955</column>
                                <column id="1">1.28679046505e-06</column>
                            </row>
                            <row id="20">
                                <column id="0">0.753969987475</column>
                                <column id="1">1.07614929016e-06</column>
                            </row>
                            <row id="21">
                                <column id="0">0.766602050207</column>
                                <column id="1">5.25327687536e-07</column>
                            </row>
                            <row id="22">
                                <column id="0">0.780627689745</column>
                                <column id="1">3.51057974242e-07</column>
                            </row>
                            <row id="23">
                                <column id="0">0.797462097555</column>
                                <column id="1">1.87490605969e-07</column>
                            </row>
                            <row id="24">
                                <column id="0">0.814299918206</column>
                                <column id="1">8.75263244096e-08</column>
                            </row>
                            <row id="25">
                                <column id="0">0.829043392</column>
                                <column id="1">2.98465016395e-08</column>
                            </row>
                            <row id="26">
                                <column id="0">0.847283890366</column>
                                <column id="1">1.33229199286e-08</column>
                            </row>
                            <row id="27">
                                <column id="0">0.863430041876</column>
                                <column id="1">4.34411152447e-09</column>
                            </row>
                            <row id="28">
                                <column id="0">0.884487271809</column>
                                <column id="1">1.13212814587e-09</column>
                            </row>
                            <row id="29">
                                <column id="0">0.905547914583</column>
                                <column id="1">2.57898441067e-10</column>
                            </row>
                            <row id="30">
                                <column id="0">0.926618795881</column>
                                <column id="1">3.92353354888e-11</column>
                            </row>
                            <row id="31">
                                <column id="0">0.950507546361</column>
                                <column id="1">3.33207036706e-12</column>
                            </row>
                        </rows>
                    </data>
                </data>
            </ElectricConductivity>
            <ElectricConductivity>
                <data>
                    <description>DC conduction rate as a function of the product &#949;s&#969;&#945;2</description>
                    <data>
                        <headers>
                            <column id="0">the product of epsilon and omega</column>
                            <column id="1">DC conduction rate (sec^-1)</column>
                        </headers>
                        <rows>
                            <row id="0">
                                <column id="0">433576.401975</column>
                                <column id="1">140678.903403</column>
                            </row>
                            <row id="1">
                                <column id="0">1102734.70416</column>
                                <column id="1">345584.361994</column>
                            </row>
                            <row id="2">
                                <column id="0">2454490.69465</column>
                                <column id="1">718712.690004</column>
                            </row>
                            <row id="3">
                                <column id="0">4532842.78414</column>
                                <column id="1">1398836.27137</column>
                            </row>
                            <row id="4">
                                <column id="0">8597316.88196</column>
                                <column id="1">2633041.62505</column>
                            </row>
                            <row id="5">
                                <column id="0">15052414.7973</column>
                                <column id="1">4637105.66634</column>
                            </row>
                            <row id="6">
                                <column id="0">26354174.7201</column>
                                <column id="1">7639250.52337</column>
                            </row>
                            <row id="7">
                                <column id="0">37275937.2031</column>
                                <column id="1">11392002.6768</column>
                            </row>
                            <row id="8">
                                <column id="0">55612669.8514</column>
                                <column id="1">16986091.042</column>
                            </row>
                        </rows>
                    </data>
                </data>
            </ElectricConductivity>
        </Electrical>
        <Thermal>
            <GlassTransitionTemperature>
                <value>-80</value>
                <unit>Celsius</unit>
            </GlassTransitionTemperature>
        </Thermal>
    </PROPERTIES>
</PolymerNanocomposite>
    